Metadata-Version: 2.1
Name: libprick
Version: 1.2.1
Summary: Python interface to the Last.FM API/website with caching support
Home-page: https://github.com/spiritualized/libprick
Download-URL: https://github.com/libprick/lastfmcache/archive/v1.2.0.tar.gz
Keywords: pricker,python,hash,sha256
Classifier: Development Status :: 5 - Production/Stable
Classifier: Intended Audience :: Developers
Classifier: Topic :: Software Development :: Build Tools
Classifier: Programming Language :: Python :: 3.11
